github_module/__init__.py
github_module/helper.py
github_modules-0.4.2.dist-info/METADATA
github_modules-0.4.2.dist-info/WHEEL
github_modules-0.4.2.dist-info/top_level.txt
github_modules-0.4.2.dist-info/RECORD
