Metadata-Version: 2.1
Name: github_modules
Version: 0.4.2
Summary: Modules for interacting with GitHub API.
Home-page: 
Author: Pavan Bhatt
Author-email: pavanhbhatt1@gmail.com
Requires-Dist: requests
